{
	"name": "CopyPipeline_ct",
	"properties": {
		"activities": [
			{
				"name": "ForEach_kol",
				"type": "ForEach",
				"dependsOn": [],
				"userProperties": [],
				"typeProperties": {
					"items": {
						"value": "@pipeline().parameters.cw_items",
						"type": "Expression"
					},
					"activities": [
						{
							"name": "Copy_kol",
							"type": "Copy",
							"dependsOn": [],
							"policy": {
								"timeout": "7.00:00:00",
								"retry": 0,
								"retryIntervalInSeconds": 30,
								"secureOutput": false,
								"secureInput": false
							},
							"userProperties": [
								{
									"name": "Source",
									"value": "SalesLT.@{item().source.table}"
								},
								{
									"name": "Destination",
									"value": "adventureworks-lt//@{item().destination.fileName}"
								}
							],
							"typeProperties": {
								"source": {
									"type": "AzureSqlSource",
									"queryTimeout": {
										"value": "@item().copySource.queryTimeout",
										"type": "Expression"
									},
									"partitionOption": "None"
								},
								"sink": {
									"type": "DelimitedTextSink",
									"storeSettings": {
										"type": "AzureBlobFSWriteSettings",
										"maxConcurrentConnections": 10,
										"blockSizeInMB": 10
									},
									"formatSettings": {
										"type": "DelimitedTextWriteSettings",
										"quoteAllText": true,
										"fileExtension": ".txt"
									}
								},
								"enableStaging": false,
								"validateDataConsistency": false
							},
							"inputs": [
								{
									"referenceName": "SourceDataset_kol",
									"type": "DatasetReference",
									"parameters": {
										"cw_table": "@item().source.table"
									}
								}
							],
							"outputs": [
								{
									"referenceName": "DestinationDataset_kol",
									"type": "DatasetReference",
									"parameters": {
										"cw_fileName": "@item().destination.fileName"
									}
								}
							]
						}
					]
				}
			}
		],
		"parameters": {
			"cw_items": {
				"type": "Array",
				"defaultValue": [
					{
						"source": {
							"table": "Address"
						},
						"destination": {
							"fileName": "SalesLTAddress"
						},
						"copySource": {
							"queryTimeout": "00:10:00"
						}
					},
					{
						"source": {
							"table": "Customer"
						},
						"destination": {
							"fileName": "SalesLTCustomer"
						},
						"copySource": {
							"queryTimeout": null
						}
					}
				]
			}
		},
		"annotations": []
	}
}